slants/__init__.py
slants/api.py
slants/data/synthexp1_data.csv
slants/data/synthexp1_delta_multiplier.csv
slants/data/synthexp1_forget_factor.csv
slants/data/synthexp1_lambda_init.csv
slants/data/synthexp1_maximum_lag.csv
slants/data/synthexp1_predict.csv
slants/data/synthexp1_random_beta.csv
slants/data/synthexp1_safe_shrink_lambda.csv
slants/data/synthexp1_shrink_step_size.csv
slants/data/synthexp1_sparse_lambda_tolerance.csv
slants/data/synthexp1_spline_info_num_Bsplines.csv
slants/data/synthexp1_spline_info_order.csv
slants/data/synthexp1_tau2_init.csv
slants/data/synthexp1_test_size.csv
slants/data/synthexp2_data.csv
slants/data/synthexp2_delta_multiplier.csv
slants/data/synthexp2_forget_factor.csv
slants/data/synthexp2_lambda_init.csv
slants/data/synthexp2_maximum_lag.csv
slants/data/synthexp2_predict.csv
slants/data/synthexp2_random_beta.csv
slants/data/synthexp2_safe_shrink_lambda.csv
slants/data/synthexp2_shrink_step_size.csv
slants/data/synthexp2_sparse_lambda_tolerance.csv
slants/data/synthexp2_spline_info_num_Bsplines.csv
slants/data/synthexp2_spline_info_order.csv
slants/data/synthexp2_tau2_init.csv
slants/data/synthexp2_test_size.csv
slants/data/synthexp3_data.csv
slants/data/synthexp3_delta_multiplier.csv
slants/data/synthexp3_forget_factor.csv
slants/data/synthexp3_lambda_init.csv
slants/data/synthexp3_maximum_lag.csv
slants/data/synthexp3_predict.csv
slants/data/synthexp3_random_beta.csv
slants/data/synthexp3_safe_shrink_lambda.csv
slants/data/synthexp3_shrink_step_size.csv
slants/data/synthexp3_sparse_lambda_tolerance.csv
slants/data/synthexp3_spline_info_num_Bsplines.csv
slants/data/synthexp3_spline_info_order.csv
slants/data/synthexp3_tau2_init.csv
slants/data/synthexp3_test_size.csv
slants/model/__init__.py
slants/model/base.py
slants/model/spline.py
slants-1.0.0.dist-info/AUTHORS.md
slants-1.0.0.dist-info/LICENSE
slants-1.0.0.dist-info/METADATA
slants-1.0.0.dist-info/WHEEL
slants-1.0.0.dist-info/top_level.txt
slants-1.0.0.dist-info/RECORD
