Metadata-Version: 2.1
Name: slants
Version: 1.0.0
Summary: Sequential Learning Algorithm for Nonlinear Time Series (SLANTS)
Home-page: https://github.com/JieGroup/slants
Author: Rachit Jas, Jiaqi Liu, Qiuyi Han, Jie Ding
Author-email: dingj@umn.edu
License: GNU GPLv3
Keywords: sequential adaptive online time series machine learning expectation maximization algorithm group lasso statistics
Platform: UNKNOWN
Classifier: Topic :: Education
Classifier: Topic :: Scientific/Engineering :: Information Analysis
Classifier: Topic :: Scientific/Engineering :: Mathematics
Classifier: Topic :: Scientific/Engineering
Classifier: License :: OSI Approved :: GNU General Public License v3 (GPLv3)
Classifier: Programming Language :: Python
Classifier: Programming Language :: Python :: 3.6
Classifier: Programming Language :: Python :: 3.7
Classifier: Programming Language :: Python :: 3.8
Classifier: Intended Audience :: Education
Classifier: Intended Audience :: Developers
Classifier: Intended Audience :: Information Technology
Classifier: Intended Audience :: Science/Research
Requires-Dist: numpy
Requires-Dist: pandas
Requires-Dist: matplotlib
